valor_lite/LICENSE
valor_lite/__init__.py
valor_lite/exceptions.py
valor_lite/schemas.py
valor_lite/cache/__init__.py
valor_lite/cache/compute.py
valor_lite/cache/ephemeral.py
valor_lite/cache/persistent.py
valor_lite/classification/__init__.py
valor_lite/classification/annotation.py
valor_lite/classification/computation.py
valor_lite/classification/evaluator.py
valor_lite/classification/loader.py
valor_lite/classification/metric.py
valor_lite/classification/numpy_compatibility.py
valor_lite/classification/shared.py
valor_lite/classification/utilities.py
valor_lite/object_detection/__init__.py
valor_lite/object_detection/annotation.py
valor_lite/object_detection/computation.py
valor_lite/object_detection/evaluator.py
valor_lite/object_detection/loader.py
valor_lite/object_detection/metric.py
valor_lite/object_detection/shared.py
valor_lite/object_detection/utilities.py
valor_lite/semantic_segmentation/__init__.py
valor_lite/semantic_segmentation/annotation.py
valor_lite/semantic_segmentation/computation.py
valor_lite/semantic_segmentation/evaluator.py
valor_lite/semantic_segmentation/loader.py
valor_lite/semantic_segmentation/metric.py
valor_lite/semantic_segmentation/shared.py
valor_lite/semantic_segmentation/utilities.py
valor_lite/text_generation/__init__.py
valor_lite/text_generation/annotation.py
valor_lite/text_generation/computation.py
valor_lite/text_generation/manager.py
valor_lite/text_generation/metric.py
valor_lite/text_generation/llm/__init__.py
valor_lite/text_generation/llm/exceptions.py
valor_lite/text_generation/llm/generation.py
valor_lite/text_generation/llm/instructions.py
valor_lite/text_generation/llm/integrations.py
valor_lite/text_generation/llm/utilities.py
valor_lite/text_generation/llm/validators.py
valor_lite-0.37.3.dist-info/METADATA
valor_lite-0.37.3.dist-info/WHEEL
valor_lite-0.37.3.dist-info/top_level.txt
valor_lite-0.37.3.dist-info/RECORD
