Metadata-Version: 2.4
Name: valor-lite
Version: 0.37.3
Summary: Evaluate machine learning models.
Project-URL: homepage, https://www.striveworks.com
Requires-Python: >=3.10
Requires-Dist: numpy
Requires-Dist: tqdm
Requires-Dist: shapely
Requires-Dist: pyarrow
Provides-Extra: nlp
Requires-Dist: evaluate; extra == "nlp"
Requires-Dist: nltk; extra == "nlp"
Requires-Dist: rouge_score; extra == "nlp"
Provides-Extra: mistral
Requires-Dist: mistralai<1.8.0,>=1.0.0; extra == "mistral"
Provides-Extra: openai
Requires-Dist: openai; extra == "openai"
Provides-Extra: docs
Requires-Dist: mkdocs; extra == "docs"
Requires-Dist: mkdocs-material; extra == "docs"
Requires-Dist: mkdocstrings; extra == "docs"
Requires-Dist: mkdocstrings-python; extra == "docs"
Requires-Dist: mkdocs-include-dir-to-nav; extra == "docs"
Requires-Dist: mkdocs-swagger-ui-tag; extra == "docs"
Provides-Extra: test
Requires-Dist: pytest; extra == "test"
Requires-Dist: coverage; extra == "test"
Requires-Dist: pre-commit; extra == "test"
Provides-Extra: benchmark
Requires-Dist: requests; extra == "benchmark"
Provides-Extra: dev
Requires-Dist: valor-lite[benchmark,docs,mistral,nlp,openai,test]; extra == "dev"
